{
  "id": "youtube_minimal",
  "name": "YouTube Minimal",
  "platform": "youtube",
  "width": 1280,
  "height": 720,
  "background": "#ffffff",
  "elements": [
    {
      "id": "bg_rect",
      "type": "rect",
      "x": 0,
      "y": 0,
      "width": 1280,
      "height": 720,
      "fill": "#ffffff",
      "cornerRadius": 0,
      "draggable": false,
      "visible": true,
      "opacity": 1
    },
    {
      "id": "left_bar",
      "type": "rect",
      "x": 0,
      "y": 0,
      "width": 16,
      "height": 720,
      "fill": "#111827",
      "cornerRadius": 0,
      "draggable": false,
      "visible": true,
      "opacity": 1
    },
    {
      "id": "title",
      "type": "text",
      "x": 80,
      "y": 240,
      "text": "Clean & Simple\nTitle Here",
      "fontSize": 100,
      "fontFamily": "Poppins",
      "color": "#111827",
      "stroke": "",
      "strokeWidth": 0,
      "fontStyle": "bold",
      "align": "left",
      "width": 1100,
      "draggable": true,
      "visible": true,
      "opacity": 1
    },
    {
      "id": "author",
      "type": "text",
      "x": 80,
      "y": 620,
      "text": "@yourchannel",
      "fontSize": 36,
      "fontFamily": "Inter",
      "color": "#6b7280",
      "stroke": "",
      "strokeWidth": 0,
      "fontStyle": "normal",
      "align": "left",
      "width": 500,
      "draggable": true,
      "visible": true,
      "opacity": 1
    }
  ],
  "imageType": "youtube_video",
  "mainTextId": "title",
  "previewUrl": "https://picsum.photos/seed/yt-min/640/360"
}